merge_into_series/__init__.py
merge_into_series/cli.py
merge_into_series/config.py
merge_into_series/file_operations.py
merge_into_series/interface.py
merge_into_series/matcher.py
merge_into_series/tvdb_scraper.py
merge_into_series-0.1.6.dist-info/licenses/LICENSE
merge_into_series-0.1.6.dist-info/METADATA
merge_into_series-0.1.6.dist-info/WHEEL
merge_into_series-0.1.6.dist-info/entry_points.txt
merge_into_series-0.1.6.dist-info/top_level.txt
merge_into_series-0.1.6.dist-info/RECORD
